{
  "id": "corporation-tax-share-dealings-investments-support-part-a-franked-investment-income-563",
  "imageSrc": "/updates/tax-engineering.png",
  "imageAlt": "Corporation Tax - Share dealings / investments support. Part A - Franked Investment Income roadmap item preview image",
  "date": "2026-06-23",
  "tags": [
    "roadmap",
    "coming-soon",
    "roadmap-built-for-every-business"
  ],
  "storyTags": [],
  "title": "Corporation Tax - Share dealings / investments support. Part A - Franked Investment Income",
  "summaryBody": "Corporation Tax - Share dealings / investments support. Part A - Franked Investment Income",
  "readMoreUrl": "https://www.freeagent.com/blog/?s=Corporation%20Tax%20-%20Share%20dealings%20%2F%20investments%20support.%20Part%20A%20-%20Franked%20Investment%20Income"
}
