{
  "id": "embed-smart-capture-within-expenses-700",
  "imageSrc": "/updates/mobile.png",
  "imageAlt": "Embed Smart Capture within expenses roadmap item preview image",
  "date": "2026-04-24",
  "tags": [
    "roadmap",
    "roadmap-status-done",
    "roadmap-drive-adoption-of-add-ons"
  ],
  "storyTags": [],
  "title": "Embed Smart Capture within expenses",
  "summaryBody": "Plan to initially release for expenses only to see how it performs. If well, then we’d look to replicate the approach for bills.",
  "detailBody": [
    "Plan to initially release for expenses only to see how it performs. If well, then we’d look to replicate the approach for bills."
  ],
  "readMoreUrl": "https://www.freeagent.com/blog/?s=Embed%20Smart%20Capture%20within%20expenses"
}
