{
  "id": "get-started-buttons-for-payment-providers-302",
  "imageSrc": "/updates/workflow.png",
  "imageAlt": "“Get started” buttons for Payment Providers roadmap item preview image",
  "date": "2024-07-02",
  "tags": [
    "roadmap"
  ],
  "storyTags": [],
  "title": "“Get started” buttons for Payment Providers",
  "summaryBody": "“Get started” buttons for Payment Providers",
  "readMoreUrl": "https://www.freeagent.com/blog/?s=%E2%80%9CGet%20started%E2%80%9D%20buttons%20for%20Payment%20Providers"
}
