{
  "id": "mtd-for-income-tax-multi-income-view-across-mtd-for-income-tax-783",
  "imageSrc": "/updates/tax-engineering.png",
  "imageAlt": "MTD for Income Tax - Multi-income view across MTD for Income Tax roadmap item preview image",
  "date": "2026-06-23",
  "tags": [
    "roadmap",
    "coming-soon"
  ],
  "storyTags": [],
  "title": "MTD for Income Tax - Multi-income view across MTD for Income Tax",
  "summaryBody": "MTD for Income Tax - Multi-income view across MTD for Income Tax",
  "readMoreUrl": "https://www.freeagent.com/blog/?s=MTD%20for%20Income%20Tax%20-%20Multi-income%20view%20across%20MTD%20for%20Income%20Tax"
}
