{
  "id": "mtd-for-income-tax-quarterly-review-approval-and-submission-789",
  "imageSrc": "/updates/mobile.png",
  "imageAlt": "MTD for Income Tax - quarterly review, approval & submission roadmap item preview image",
  "date": "2026-06-23",
  "tags": [
    "roadmap",
    "coming-soon",
    "roadmap-status-build",
    "roadmap-get-mtd-done"
  ],
  "storyTags": [],
  "title": "MTD for Income Tax - quarterly review, approval & submission",
  "summaryBody": "Tax Eng will build the API in C2. We’ll build in late-C2-C3. Positioning our comms as ‘coming soon’",
  "detailBody": [
    "Tax Eng will build the API in C2. We’ll build in late-C2-C3. Positioning our comms as ‘coming soon’"
  ],
  "readMoreUrl": "https://www.freeagent.com/blog/?s=MTD%20for%20Income%20Tax%20-%20quarterly%20review%2C%20approval%20%26%20submission"
}
