{
  "id": "prevent-personal-bank-accounts-in-uk-ltds-and-llps-71",
  "imageSrc": "/updates/banking.png",
  "imageAlt": "Prevent personal bank accounts in UK LTDs and LLPs roadmap item preview image",
  "date": "2026-06-23",
  "tags": [
    "roadmap",
    "coming-soon",
    "roadmap-a-solid-foundation"
  ],
  "storyTags": [],
  "title": "Prevent personal bank accounts in UK LTDs and LLPs",
  "summaryBody": "Prevent personal bank accounts in UK LTDs and LLPs",
  "readMoreUrl": "https://www.freeagent.com/blog/?s=Prevent%20personal%20bank%20accounts%20in%20UK%20LTDs%20and%20LLPs"
}
