{
  "id": "self-assessment-foreign-income-or-gains-sa106-577",
  "imageSrc": "/updates/tax-engineering.png",
  "imageAlt": "Self Assessment - Foreign Income or gains (SA106) roadmap item preview image",
  "date": "2026-06-23",
  "tags": [
    "roadmap",
    "coming-soon"
  ],
  "storyTags": [],
  "title": "Self Assessment - Foreign Income or gains (SA106)",
  "summaryBody": "Self Assessment - Foreign Income or gains (SA106)",
  "readMoreUrl": "https://www.freeagent.com/blog/?s=Self%20Assessment%20-%20Foreign%20Income%20or%20gains%20(SA106)"
}
