{
  "id": "self-assessment-dynamically-refresh-error-messages-and-notices-832",
  "imageSrc": "/updates/tax-engineering.png",
  "imageAlt": "Self Assessment - Dynamically refresh error messages and notices roadmap item preview image",
  "date": "2026-06-23",
  "tags": [
    "roadmap",
    "coming-soon"
  ],
  "storyTags": [],
  "title": "Self Assessment - Dynamically refresh error messages and notices",
  "summaryBody": "Self Assessment - Dynamically refresh error messages and notices",
  "readMoreUrl": "https://www.freeagent.com/blog/?s=Self%20Assessment%20-%20Dynamically%20refresh%20error%20messages%20and%20notices"
}
