{
  "id": "start-accepting-online-payments-flying-start-task-273",
  "imageSrc": "/updates/default-2.png",
  "imageAlt": "“Start accepting online payments” Flying Start task roadmap item preview image",
  "date": "2023-10-19",
  "tags": [
    "roadmap"
  ],
  "storyTags": [],
  "title": "“Start accepting online payments” Flying Start task",
  "summaryBody": "“Start accepting online payments” Flying Start task",
  "readMoreUrl": "https://www.freeagent.com/blog/?s=%E2%80%9CStart%20accepting%20online%20payments%E2%80%9D%20Flying%20Start%20task"
}
